xlsxreport/__init__.py
xlsxreport/appdir.py
xlsxreport/builder.py
xlsxreport/compiler.py
xlsxreport/schemas.py
xlsxreport/validate.py
xlsxreport/writer.py
xlsxreport/default_templates/fragpipe.yaml
xlsxreport/default_templates/maxquant.yaml
xlsxreport/scripts/__init__.py
xlsxreport/scripts/appdir.py
xlsxreport/scripts/cli.py
xlsxreport/scripts/compile_excel.py
xlsxreport/scripts/validate.py
xlsxreport/template/__init__.py
xlsxreport/template/_repr.py
xlsxreport/template/formats.py
xlsxreport/template/section.py
xlsxreport/template/sections.py
xlsxreport/template/settings.py
xlsxreport/template/template.py
xlsxreport-0.1.1.dist-info/LICENSE
xlsxreport-0.1.1.dist-info/METADATA
xlsxreport-0.1.1.dist-info/WHEEL
xlsxreport-0.1.1.dist-info/entry_points.txt
xlsxreport-0.1.1.dist-info/top_level.txt
xlsxreport-0.1.1.dist-info/RECORD
