Metadata-Version: 2.1
Name: xlsxreport
Version: 0.1.1
Summary: Automated generation of formatted excel reports from MS results
Author-email: "David M. Hollenstein" <hollenstein.david@gmail.com>
License: Apache-2.0
Keywords: mass spectrometry,proteomics,report,excel
Classifier: Development Status :: 3 - Alpha
Classifier: License :: OSI Approved :: Apache Software License
Classifier: Programming Language :: Python
Classifier: Topic :: Scientific/Engineering :: Bio-Informatics
Requires-Python: >=3.9
License-File: LICENSE
Requires-Dist: cerberus>=1.3.5
Requires-Dist: click>=8.0.4
Requires-Dist: numpy>=1.21.5
Requires-Dist: pandas>=1.4.4
Requires-Dist: platformdirs>=3
Requires-Dist: pyyaml>=6.0
Requires-Dist: xlsxwriter>=3.1.2
Provides-Extra: dev
Requires-Dist: nox; extra == "dev"
Requires-Dist: pytest>=7.1.2; extra == "dev"
Requires-Dist: openpyxl>=3.0.10; extra == "dev"
Provides-Extra: tests
Requires-Dist: pytest>=7.1.2; extra == "tests"
Requires-Dist: openpyxl>=3.0.10; extra == "tests"
